{
    "canvas_config": {
        "width": 1080,
        "height": 1920,
        "ratio": "original"
    },
    "color_space": 0,
    "config": {
        "adjust_max_index": 1,
        "attachment_info": [],
        "combination_max_index": 1,
        "export_range": null,
        "extract_audio_last_index": 1,
        "lyrics_recognition_id": "",
        "lyrics_sync": true,
        "lyrics_taskinfo": [],
        "maintrack_adsorb": true,
        "material_save_mode": 0,
        "multi_language_current": "none",
        "multi_language_list": [],
        "multi_language_main": "none",
        "multi_language_mode": "none",
        "original_sound_last_index": 1,
        "record_audio_last_index": 1,
        "sticker_max_index": 1,
        "subtitle_keywords_config": null,
        "subtitle_recognition_id": "",
        "subtitle_sync": true,
        "subtitle_taskinfo": [],
        "system_font_list": [],
        "video_mute": false,
        "zoom_info_params": null
    },
    "cover": null,
    "create_time": 0,
    "duration": 25000000,
    "extra_info": null,
    "fps": 30,
    "free_render_index_mode_on": false,
    "group_container": null,
    "id": "91E08AC5-22FB-47e2-9AA0-7DC300FAEA2B",
    "keyframe_graph_list": [],
    "keyframes": {
        "adjusts": [],
        "audios": [],
        "effects": [],
        "filters": [],
        "handwrites": [],
        "stickers": [],
        "texts": [],
        "videos": []
    },
    "last_modified_platform": {
        "app_id": 359289,
        "app_source": "cc",
        "app_version": "6.5.0",
        "device_id": "c4ca4238a0b923820dcc509a6f75849b",
        "hard_disk_id": "307563e0192a94465c0e927fbc482942",
        "mac_address": "c3371f2d4fb02791c067ce44d8fb4ed5",
        "os": "mac",
        "os_version": "15.5"
    },
    "materials": {
        "ai_translates": [],
        "audio_balances": [],
        "audio_effects": [],
        "audio_fades": [],
        "audio_track_indexes": [],
        "audios": [
            {
                "app_id": 0,
                "category_id": "",
                "category_name": "local",
                "check_flag": 1,
                "copyright_limit_type": "none",
                "duration": 0,
                "effect_id": "",
                "formula_id": "",
                "id": "86272ea082fb30338e2109ab31f77154",
                "intensifies_path": "",
                "is_ai_clone_tone": false,
                "is_text_edit_overdub": false,
                "is_ugc": false,
                "local_material_id": "86272ea082fb30338e2109ab31f77154",
                "music_id": "86272ea082fb30338e2109ab31f77154",
                "name": "audio_6b17dc78701f1d15.mp3",
                "path": "C:\\Users\\86134\\AppData\\Local\\JianyingPro\\User Data\\Projects\\com.lveditor.draft\\dfd_cat_1779492619_a4c0be08\\assets\\audio\\audio_6b17dc78701f1d15.mp3",
                "remote_url": "D:\\AI_Agents\\video-tools\\out\\v3_20260523_072959\\voiceover.mp3",
                "query": "",
                "request_id": "",
                "resource_id": "",
                "search_id": "",
                "source_from": "",
                "source_platform": 0,
                "team_id": "",
                "text_id": "",
                "tone_category_id": "",
                "tone_category_name": "",
                "tone_effect_id": "",
                "tone_effect_name": "",
                "tone_platform": "",
                "tone_second_category_id": "",
                "tone_second_category_name": "",
                "tone_speaker": "",
                "tone_type": "",
                "type": "extract_music",
                "video_id": "",
                "wave_points": []
            }
        ],
        "beats": [],
        "canvases": [],
        "chromas": [],
        "color_curves": [],
        "digital_humans": [],
        "drafts": [],
        "effects": [],
        "flowers": [],
        "green_screens": [],
        "handwrites": [],
        "hsl": [],
        "images": [],
        "log_color_wheels": [],
        "loudnesses": [],
        "manual_deformations": [],
        "material_animations": [],
        "material_colors": [],
        "multi_language_refs": [],
        "placeholders": [],
        "plugin_effects": [],
        "primary_color_wheels": [],
        "realtime_denoises": [],
        "shapes": [],
        "smart_crops": [],
        "smart_relights": [],
        "sound_channel_mappings": [],
        "speeds": [
            {
                "curve_speed": null,
                "id": "fc8f934bb3d14493abb92862e230f8db",
                "mode": 0,
                "speed": 1.0,
                "type": "speed"
            },
            {
                "curve_speed": null,
                "id": "b7278e93d33f4397812e474ed0048e31",
                "mode": 0,
                "speed": 1.0,
                "type": "speed"
            },
            {
                "curve_speed": null,
                "id": "db9f29a5219843b2b0325bbe9a3605f8",
                "mode": 0,
                "speed": 1.0,
                "type": "speed"
            }
        ],
        "stickers": [],
        "tail_leaders": [],
        "text_templates": [],
        "texts": [
            {
                "id": "99698edbdd0a475e915f09e6ba70fa7c",
                "content": "{\"styles\": [{\"fill\": {\"alpha\": 1.0, \"content\": {\"render_type\": \"solid\", \"solid\": {\"alpha\": 1.0, \"color\": [1.0, 0.0, 0.0]}}}, \"range\": [0, 28], \"size\": 8.0, \"bold\": false, \"italic\": false, \"underline\": false, \"strokes\": [{\"content\": {\"solid\": {\"alpha\": 1.0, \"color\": [0.0, 0.0, 0.0]}}, \"width\": 0.004}], \"font\": {\"id\": \"7290445778273702455\", \"path\": \"C:/文轩体.ttf\"}}], \"text\": \"\\\"Meet the future of cinema.\\\"\"}",
                "typesetting": 0,
                "alignment": 1,
                "letter_spacing": 0.0,
                "line_spacing": 0.02,
                "line_feed": 1,
                "line_max_width": 0.82,
                "force_apply_line_max_width": false,
                "check_flag": 15,
                "type": "text",
                "fixed_width": -1,
                "fixed_height": -1
            },
            {
                "id": "4afe200799fb4075b9eb583d91dea018",
                "content": "{\"styles\": [{\"fill\": {\"alpha\": 1.0, \"content\": {\"render_type\": \"solid\", \"solid\": {\"alpha\": 1.0, \"color\": [1.0, 0.0, 0.0]}}}, \"range\": [0, 26], \"size\": 8.0, \"bold\": false, \"italic\": false, \"underline\": false, \"strokes\": [{\"content\": {\"solid\": {\"alpha\": 1.0, \"color\": [0.0, 0.0, 0.0]}}, \"width\": 0.004}], \"font\": {\"id\": \"7290445778273702455\", \"path\": \"C:/文轩体.ttf\"}}], \"text\": \"\\\"From concept to reality.\\\"\"}",
                "typesetting": 0,
                "alignment": 1,
                "letter_spacing": 0.0,
                "line_spacing": 0.02,
                "line_feed": 1,
                "line_max_width": 0.82,
                "force_apply_line_max_width": false,
                "check_flag": 15,
                "type": "text",
                "fixed_width": -1,
                "fixed_height": -1
            },
            {
                "id": "ecd9a9d7e4064a869f72c120c46cea90",
                "content": "{\"styles\": [{\"fill\": {\"alpha\": 1.0, \"content\": {\"render_type\": \"solid\", \"solid\": {\"alpha\": 1.0, \"color\": [1.0, 0.0, 0.0]}}}, \"range\": [0, 35], \"size\": 8.0, \"bold\": false, \"italic\": false, \"underline\": false, \"strokes\": [{\"content\": {\"solid\": {\"alpha\": 1.0, \"color\": [0.0, 0.0, 0.0]}}, \"width\": 0.004}], \"font\": {\"id\": \"7290445778273702455\", \"path\": \"C:/文轩体.ttf\"}}], \"text\": \"\\\"Automated production, zero error.\\\"\"}",
                "typesetting": 0,
                "alignment": 1,
                "letter_spacing": 0.0,
                "line_spacing": 0.02,
                "line_feed": 1,
                "line_max_width": 0.82,
                "force_apply_line_max_width": false,
                "check_flag": 15,
                "type": "text",
                "fixed_width": -1,
                "fixed_height": -1
            },
            {
                "id": "3b258b31bd03479e8051ee5ba60daaa5",
                "content": "{\"styles\": [{\"fill\": {\"alpha\": 1.0, \"content\": {\"render_type\": \"solid\", \"solid\": {\"alpha\": 1.0, \"color\": [1.0, 0.0, 0.0]}}}, \"range\": [0, 30], \"size\": 8.0, \"bold\": false, \"italic\": false, \"underline\": false, \"strokes\": [{\"content\": {\"solid\": {\"alpha\": 1.0, \"color\": [0.0, 0.0, 0.0]}}, \"width\": 0.004}], \"font\": {\"id\": \"7290445778273702455\", \"path\": \"C:/文轩体.ttf\"}}], \"text\": \"\\\"Step into the virtual world.\\\"\"}",
                "typesetting": 0,
                "alignment": 1,
                "letter_spacing": 0.0,
                "line_spacing": 0.02,
                "line_feed": 1,
                "line_max_width": 0.82,
                "force_apply_line_max_width": false,
                "check_flag": 15,
                "type": "text",
                "fixed_width": -1,
                "fixed_height": -1
            },
            {
                "id": "7017c7cce6404dd5b0c4e8e9cb505989",
                "content": "{\"styles\": [{\"fill\": {\"alpha\": 1.0, \"content\": {\"render_type\": \"solid\", \"solid\": {\"alpha\": 1.0, \"color\": [1.0, 0.0, 0.0]}}}, \"range\": [0, 40], \"size\": 8.0, \"bold\": false, \"italic\": false, \"underline\": false, \"strokes\": [{\"content\": {\"solid\": {\"alpha\": 1.0, \"color\": [0.0, 0.0, 0.0]}}, \"width\": 0.004}], \"font\": {\"id\": \"7290445778273702455\", \"path\": \"C:/文轩体.ttf\"}}], \"text\": \"\\\"Creating scenes, one stroke at a time.\\\"\"}",
                "typesetting": 0,
                "alignment": 1,
                "letter_spacing": 0.0,
                "line_spacing": 0.02,
                "line_feed": 1,
                "line_max_width": 0.82,
                "force_apply_line_max_width": false,
                "check_flag": 15,
                "type": "text",
                "fixed_width": -1,
                "fixed_height": -1
            }
        ],
        "time_marks": [],
        "transitions": [
            {
                "category_id": "",
                "category_name": "",
                "duration": 500000,
                "effect_id": "392FD26E-A514-4d0f-8950-EA4A20CB407C",
                "id": "99072f3b4b144b008b618b4dcd74b3e3",
                "is_overlap": false,
                "name": "Dissolve",
                "platform": "all",
                "resource_id": "6724846004274729480",
                "type": "transition"
            }
        ],
        "video_effects": [],
        "video_trackings": [],
        "videos": [
            {
                "audio_fade": null,
                "category_id": "",
                "category_name": "local",
                "check_flag": 63487,
                "crop": {
                    "upper_left_x": 0.0,
                    "upper_left_y": 0.0,
                    "upper_right_x": 1.0,
                    "upper_right_y": 0.0,
                    "lower_left_x": 0.0,
                    "lower_left_y": 1.0,
                    "lower_right_x": 1.0,
                    "lower_right_y": 1.0
                },
                "crop_ratio": "free",
                "crop_scale": 1.0,
                "duration": 0,
                "height": 1080,
                "id": "58ea2f1ec950385993fa90408c73e6c7",
                "local_material_id": "",
                "material_id": "58ea2f1ec950385993fa90408c73e6c7",
                "material_name": "video_3d8aca4d08c40c36.mp4",
                "media_path": "",
                "path": "C:\\Users\\86134\\AppData\\Local\\JianyingPro\\User Data\\Projects\\com.lveditor.draft\\dfd_cat_1779492619_a4c0be08\\assets\\video\\video_3d8aca4d08c40c36.mp4",
                "remote_url": "D:\\AI_Agents\\video-tools\\out\\v3_20260523_072959\\placeholder_0.mp4",
                "type": "video",
                "width": 1920
            },
            {
                "audio_fade": null,
                "category_id": "",
                "category_name": "local",
                "check_flag": 63487,
                "crop": {
                    "upper_left_x": 0.0,
                    "upper_left_y": 0.0,
                    "upper_right_x": 1.0,
                    "upper_right_y": 0.0,
                    "lower_left_x": 0.0,
                    "lower_left_y": 1.0,
                    "lower_right_x": 1.0,
                    "lower_right_y": 1.0
                },
                "crop_ratio": "free",
                "crop_scale": 1.0,
                "duration": 0,
                "height": 1080,
                "id": "51e73e3e80b03734824c6ec6d93b53cb",
                "local_material_id": "",
                "material_id": "51e73e3e80b03734824c6ec6d93b53cb",
                "material_name": "video_45a81298d4673741.mp4",
                "media_path": "",
                "path": "C:\\Users\\86134\\AppData\\Local\\JianyingPro\\User Data\\Projects\\com.lveditor.draft\\dfd_cat_1779492619_a4c0be08\\assets\\video\\video_45a81298d4673741.mp4",
                "remote_url": "D:\\AI_Agents\\video-tools\\out\\v3_20260523_072959\\placeholder_4.mp4",
                "type": "video",
                "width": 1920
            }
        ],
        "vocal_beautifys": [],
        "vocal_separations": [],
        "common_mask": []
    },
    "mutable_config": null,
    "name": "",
    "new_version": "110.0.0",
    "relationships": [],
    "render_index_track_mode_on": false,
    "retouch_cover": null,
    "source": "default",
    "static_cover_image_path": "",
    "time_marks": null,
    "tracks": [
        {
            "attribute": 0,
            "flag": 0,
            "id": "90235823163a40ba9cc7eb6912505d1b",
            "is_default_name": false,
            "name": "video",
            "segments": [],
            "type": "video"
        },
        {
            "attribute": 0,
            "flag": 0,
            "id": "a61db9c68dbe492798d49649aa84b264",
            "is_default_name": false,
            "name": "video_0",
            "segments": [
                {
                    "enable_adjust": true,
                    "enable_color_correct_adjust": false,
                    "enable_color_curves": true,
                    "enable_color_match_adjust": false,
                    "enable_color_wheels": true,
                    "enable_lut": true,
                    "enable_smart_color_adjust": false,
                    "last_nonzero_volume": 1.0,
                    "reverse": false,
                    "track_attribute": 0,
                    "track_render_index": 0,
                    "visible": true,
                    "id": "1809a6d24d904328b0b59574ff980282",
                    "material_id": "58ea2f1ec950385993fa90408c73e6c7",
                    "target_timerange": {
                        "start": 0,
                        "duration": 0
                    },
                    "common_keyframes": [],
                    "keyframe_refs": [],
                    "source_timerange": {
                        "start": 0,
                        "duration": 0
                    },
                    "speed": 1.0,
                    "volume": 1.0,
                    "extra_material_refs": [
                        "fc8f934bb3d14493abb92862e230f8db"
                    ],
                    "clip": {
                        "alpha": 1.0,
                        "flip": {
                            "horizontal": false,
                            "vertical": false
                        },
                        "rotation": 0.0,
                        "scale": {
                            "x": 1.0,
                            "y": 1.0
                        },
                        "transform": {
                            "x": 0.0,
                            "y": 0.0
                        }
                    },
                    "uniform_scale": {
                        "on": true,
                        "value": 1.0
                    },
                    "hdr_settings": {
                        "intensity": 1.0,
                        "mode": 1,
                        "nits": 1000
                    },
                    "render_index": 0
                }
            ],
            "type": "video"
        },
        {
            "attribute": 0,
            "flag": 0,
            "id": "5e503254a56a446985689aad9f373b86",
            "is_default_name": false,
            "name": "video_1",
            "segments": [],
            "type": "video"
        },
        {
            "attribute": 0,
            "flag": 0,
            "id": "634f5efea323420d99bf0b18bd49e7e8",
            "is_default_name": false,
            "name": "video_2",
            "segments": [],
            "type": "video"
        },
        {
            "attribute": 0,
            "flag": 0,
            "id": "b683a88652e14443885d87b80811b100",
            "is_default_name": false,
            "name": "video_3",
            "segments": [],
            "type": "video"
        },
        {
            "attribute": 0,
            "flag": 0,
            "id": "2d700bf2ce7f4ca8aa9a3374b972470b",
            "is_default_name": false,
            "name": "video_4",
            "segments": [
                {
                    "enable_adjust": true,
                    "enable_color_correct_adjust": false,
                    "enable_color_curves": true,
                    "enable_color_match_adjust": false,
                    "enable_color_wheels": true,
                    "enable_lut": true,
                    "enable_smart_color_adjust": false,
                    "last_nonzero_volume": 1.0,
                    "reverse": false,
                    "track_attribute": 0,
                    "track_render_index": 0,
                    "visible": true,
                    "id": "e6b4dcc991a74704bcb0b853a212dd93",
                    "material_id": "51e73e3e80b03734824c6ec6d93b53cb",
                    "target_timerange": {
                        "start": 20000000,
                        "duration": 0
                    },
                    "common_keyframes": [],
                    "keyframe_refs": [],
                    "source_timerange": {
                        "start": 0,
                        "duration": 0
                    },
                    "speed": 1.0,
                    "volume": 1.0,
                    "extra_material_refs": [
                        "b7278e93d33f4397812e474ed0048e31",
                        "99072f3b4b144b008b618b4dcd74b3e3"
                    ],
                    "clip": {
                        "alpha": 1.0,
                        "flip": {
                            "horizontal": false,
                            "vertical": false
                        },
                        "rotation": 0.0,
                        "scale": {
                            "x": 1.0,
                            "y": 1.0
                        },
                        "transform": {
                            "x": 0.0,
                            "y": 0.0
                        }
                    },
                    "uniform_scale": {
                        "on": true,
                        "value": 1.0
                    },
                    "hdr_settings": {
                        "intensity": 1.0,
                        "mode": 1,
                        "nits": 1000
                    },
                    "render_index": 0
                }
            ],
            "type": "video"
        },
        {
            "attribute": 0,
            "flag": 0,
            "id": "7e61ebfaf4ff469bb9b7cd0c50bc0580",
            "is_default_name": false,
            "name": "audio_main",
            "segments": [
                {
                    "enable_adjust": true,
                    "enable_color_correct_adjust": false,
                    "enable_color_curves": true,
                    "enable_color_match_adjust": false,
                    "enable_color_wheels": true,
                    "enable_lut": true,
                    "enable_smart_color_adjust": false,
                    "last_nonzero_volume": 1.0,
                    "reverse": false,
                    "track_attribute": 0,
                    "track_render_index": 0,
                    "visible": true,
                    "id": "4933a3f936254d808a4f5d3716485210",
                    "material_id": "86272ea082fb30338e2109ab31f77154",
                    "target_timerange": {
                        "start": 0,
                        "duration": 0
                    },
                    "common_keyframes": [],
                    "keyframe_refs": [],
                    "source_timerange": {
                        "start": 0,
                        "duration": 0
                    },
                    "speed": 1.0,
                    "volume": 1.2,
                    "extra_material_refs": [
                        "db9f29a5219843b2b0325bbe9a3605f8"
                    ],
                    "clip": null,
                    "hdr_settings": null,
                    "render_index": 0
                }
            ],
            "type": "audio"
        },
        {
            "attribute": 0,
            "flag": 0,
            "id": "d8e1f38891224323a3bc5ba704fcd9bd",
            "is_default_name": false,
            "name": "sub_0",
            "segments": [
                {
                    "enable_adjust": true,
                    "enable_color_correct_adjust": false,
                    "enable_color_curves": true,
                    "enable_color_match_adjust": false,
                    "enable_color_wheels": true,
                    "enable_lut": true,
                    "enable_smart_color_adjust": false,
                    "last_nonzero_volume": 1.0,
                    "reverse": false,
                    "track_attribute": 0,
                    "track_render_index": 0,
                    "visible": true,
                    "id": "f7668c9750c64c42960f7c6a9bbd15fe",
                    "material_id": "99698edbdd0a475e915f09e6ba70fa7c",
                    "target_timerange": {
                        "start": 0,
                        "duration": 5000000
                    },
                    "common_keyframes": [],
                    "keyframe_refs": [],
                    "source_timerange": null,
                    "speed": 1.0,
                    "volume": 1.0,
                    "extra_material_refs": [
                        "3c8d4218d9214a62b33f9500ee461842"
                    ],
                    "clip": {
                        "alpha": 1.0,
                        "flip": {
                            "horizontal": false,
                            "vertical": false
                        },
                        "rotation": 0.0,
                        "scale": {
                            "x": 1.0,
                            "y": 1.0
                        },
                        "transform": {
                            "x": 0.5,
                            "y": -0.7
                        }
                    },
                    "uniform_scale": {
                        "on": true,
                        "value": 1.0
                    },
                    "render_index": 15000
                }
            ],
            "type": "text"
        },
        {
            "attribute": 0,
            "flag": 0,
            "id": "8f71af7ec80843e2a0749392c34d6fd7",
            "is_default_name": false,
            "name": "sub_1",
            "segments": [
                {
                    "enable_adjust": true,
                    "enable_color_correct_adjust": false,
                    "enable_color_curves": true,
                    "enable_color_match_adjust": false,
                    "enable_color_wheels": true,
                    "enable_lut": true,
                    "enable_smart_color_adjust": false,
                    "last_nonzero_volume": 1.0,
                    "reverse": false,
                    "track_attribute": 0,
                    "track_render_index": 0,
                    "visible": true,
                    "id": "855d083cfc4a41ef9fb79797866f602f",
                    "material_id": "4afe200799fb4075b9eb583d91dea018",
                    "target_timerange": {
                        "start": 5000000,
                        "duration": 5000000
                    },
                    "common_keyframes": [],
                    "keyframe_refs": [],
                    "source_timerange": null,
                    "speed": 1.0,
                    "volume": 1.0,
                    "extra_material_refs": [
                        "cd2d2e346c364359b289b1c0cfe61af0"
                    ],
                    "clip": {
                        "alpha": 1.0,
                        "flip": {
                            "horizontal": false,
                            "vertical": false
                        },
                        "rotation": 0.0,
                        "scale": {
                            "x": 1.0,
                            "y": 1.0
                        },
                        "transform": {
                            "x": 0.5,
                            "y": -0.7
                        }
                    },
                    "uniform_scale": {
                        "on": true,
                        "value": 1.0
                    },
                    "render_index": 15000
                }
            ],
            "type": "text"
        },
        {
            "attribute": 0,
            "flag": 0,
            "id": "788cebf7548a43e2b1d77130b859e8b4",
            "is_default_name": false,
            "name": "sub_2",
            "segments": [
                {
                    "enable_adjust": true,
                    "enable_color_correct_adjust": false,
                    "enable_color_curves": true,
                    "enable_color_match_adjust": false,
                    "enable_color_wheels": true,
                    "enable_lut": true,
                    "enable_smart_color_adjust": false,
                    "last_nonzero_volume": 1.0,
                    "reverse": false,
                    "track_attribute": 0,
                    "track_render_index": 0,
                    "visible": true,
                    "id": "2474507480714f338fa4c0567add211e",
                    "material_id": "ecd9a9d7e4064a869f72c120c46cea90",
                    "target_timerange": {
                        "start": 10000000,
                        "duration": 5000000
                    },
                    "common_keyframes": [],
                    "keyframe_refs": [],
                    "source_timerange": null,
                    "speed": 1.0,
                    "volume": 1.0,
                    "extra_material_refs": [
                        "d6e28881e14d49ba94e768fd751e5007"
                    ],
                    "clip": {
                        "alpha": 1.0,
                        "flip": {
                            "horizontal": false,
                            "vertical": false
                        },
                        "rotation": 0.0,
                        "scale": {
                            "x": 1.0,
                            "y": 1.0
                        },
                        "transform": {
                            "x": 0.5,
                            "y": -0.7
                        }
                    },
                    "uniform_scale": {
                        "on": true,
                        "value": 1.0
                    },
                    "render_index": 15000
                }
            ],
            "type": "text"
        },
        {
            "attribute": 0,
            "flag": 0,
            "id": "0ad79ae31a1b42d38f7c1c395c604a16",
            "is_default_name": false,
            "name": "sub_3",
            "segments": [
                {
                    "enable_adjust": true,
                    "enable_color_correct_adjust": false,
                    "enable_color_curves": true,
                    "enable_color_match_adjust": false,
                    "enable_color_wheels": true,
                    "enable_lut": true,
                    "enable_smart_color_adjust": false,
                    "last_nonzero_volume": 1.0,
                    "reverse": false,
                    "track_attribute": 0,
                    "track_render_index": 0,
                    "visible": true,
                    "id": "a95cae000e234c14a563c682b47b2bb0",
                    "material_id": "3b258b31bd03479e8051ee5ba60daaa5",
                    "target_timerange": {
                        "start": 15000000,
                        "duration": 5000000
                    },
                    "common_keyframes": [],
                    "keyframe_refs": [],
                    "source_timerange": null,
                    "speed": 1.0,
                    "volume": 1.0,
                    "extra_material_refs": [
                        "89ce38f1190c41afbe996abc0cfa3a81"
                    ],
                    "clip": {
                        "alpha": 1.0,
                        "flip": {
                            "horizontal": false,
                            "vertical": false
                        },
                        "rotation": 0.0,
                        "scale": {
                            "x": 1.0,
                            "y": 1.0
                        },
                        "transform": {
                            "x": 0.5,
                            "y": -0.7
                        }
                    },
                    "uniform_scale": {
                        "on": true,
                        "value": 1.0
                    },
                    "render_index": 15000
                }
            ],
            "type": "text"
        },
        {
            "attribute": 0,
            "flag": 0,
            "id": "0d51946e4c6e43d1847c06a4203b9bd5",
            "is_default_name": false,
            "name": "sub_4",
            "segments": [
                {
                    "enable_adjust": true,
                    "enable_color_correct_adjust": false,
                    "enable_color_curves": true,
                    "enable_color_match_adjust": false,
                    "enable_color_wheels": true,
                    "enable_lut": true,
                    "enable_smart_color_adjust": false,
                    "last_nonzero_volume": 1.0,
                    "reverse": false,
                    "track_attribute": 0,
                    "track_render_index": 0,
                    "visible": true,
                    "id": "af17061a00e544e48a58bbee3726c014",
                    "material_id": "7017c7cce6404dd5b0c4e8e9cb505989",
                    "target_timerange": {
                        "start": 20000000,
                        "duration": 5000000
                    },
                    "common_keyframes": [],
                    "keyframe_refs": [],
                    "source_timerange": null,
                    "speed": 1.0,
                    "volume": 1.0,
                    "extra_material_refs": [
                        "57df5f3b9b904b8d94c0b1d8954c4977"
                    ],
                    "clip": {
                        "alpha": 1.0,
                        "flip": {
                            "horizontal": false,
                            "vertical": false
                        },
                        "rotation": 0.0,
                        "scale": {
                            "x": 1.0,
                            "y": 1.0
                        },
                        "transform": {
                            "x": 0.5,
                            "y": -0.7
                        }
                    },
                    "uniform_scale": {
                        "on": true,
                        "value": 1.0
                    },
                    "render_index": 15000
                }
            ],
            "type": "text"
        }
    ],
    "update_time": 0,
    "version": 360000,
    "platform": {
        "app_id": 359289,
        "app_source": "cc",
        "app_version": "6.5.0",
        "device_id": "c4ca4238a0b923820dcc509a6f75849b",
        "hard_disk_id": "307563e0192a94465c0e927fbc482942",
        "mac_address": "c3371f2d4fb02791c067ce44d8fb4ed5",
        "os": "mac",
        "os_version": "15.5"
    }
}